Metadata-Version: 2.1
Name: lib-dzne-data
Version: 0.2.0
Summary: Libary for handling data. 
Author-email: Johannes <johannes-programming@posteo.org>
License: The MIT License (MIT)
Project-URL: Download, https://pypi.org/project/lib-dzne-data/#files
Project-URL: Source, https://github.com/johannes-programming/lib_dzne_data
Classifier: License :: OSI Approved :: MIT License
Classifier: Programming Language :: Python
Classifier: Programming Language :: Python :: 3
Requires-Python: >=3.11
License-File: LICENSE.txt
Requires-Dist: pandas >=1.4.2
Requires-Dist: Bio >=1.5.3
Requires-Dist: na-quantors >=1.0
